beancount-degiro/__init__.py
beancount-degiro/degiro.py
beancount-degiro/degiro_de.py
beancount-degiro/stockutil.py
beancount_degiro/__init__.py
beancount_degiro/degiro.py
beancount_degiro/degiro_de.py
beancount_degiro/degiro_lang.py
beancount_degiro/stockutil.py
beancount_degiro-0.0.2.dist-info/LICENSE
beancount_degiro-0.0.2.dist-info/METADATA
beancount_degiro-0.0.2.dist-info/WHEEL
beancount_degiro-0.0.2.dist-info/top_level.txt
beancount_degiro-0.0.2.dist-info/RECORD
