Metadata-Version: 2.1
Name: beancount-degiro
Version: 0.0.2
Summary: Degiro trading account importer for Beancount
Home-page: https://gitlab.com/szabootibor/beancount-degiro
Author: Tibor Szabó
Author-email: szabootibor@gmail.com
License: UNKNOWN
Project-URL: Bug Tracker, https://gitlab.com/szabootibor/beancount-degiro/issues
Platform: UNKNOWN
Classifier: Programming Language :: Python :: 3
Classifier: License :: OSI Approved :: GNU General Public License v3 or later (GPLv3+)
Classifier: Operating System :: OS Independent
Requires-Python: >=3.6
License-File: LICENSE
Requires-Dist: beancount (==2.3.4)
Requires-Dist: pandas (==1.2.4)
